icgc_survival/__init__.py
icgc_survival/download_helper.py
icgc_survival/feature_creator.py
icgc_survival/label_creator.py
icgc_survival/survival_analysis.py
icgc_survival-0.2.3.dist-info/LICENSE.txt
icgc_survival-0.2.3.dist-info/METADATA
icgc_survival-0.2.3.dist-info/WHEEL
icgc_survival-0.2.3.dist-info/top_level.txt
icgc_survival-0.2.3.dist-info/RECORD
