Metadata-Version: 2.1
Name: icgc-survival
Version: 0.2.3
Summary: A framework for survival prediction and analysis of ICGC datasets
Home-page: https://github.com/julianspaeth/icgc-survival
Author: Julian Späth
Author-email: spaethju@posteo.de
License: MIT License
Download-URL: https://github.com/julianspaeth/icgc-survival/archive/v0.1.tar.gz
Keywords: survival-analysis,survival-prediction,machine-learning,random-survival-forest,icgc
Platform: UNKNOWN
Classifier: Development Status :: 3 - Alpha
Classifier: Topic :: Software Development :: Build Tools
Classifier: License :: OSI Approved :: MIT License
Classifier: Programming Language :: Python :: 3.5
Classifier: Programming Language :: Python :: 3.6
Classifier: Programming Language :: Python :: 3.7
Requires-Dist: requests
Requires-Dist: pandas
Requires-Dist: lifelines
Requires-Dist: numpy
Requires-Dist: random-survival-forest
